{
    "openapi": "3.0.0",
    "info": {
        "title": "API Kalidou GUISSE",
        "description": "Documentation de mon API Laravel pour la gestion des clients et comptes",
        "version": "0.1"
    },
    "servers": [
        {
            "url": "http://localhost:8000/guisse/v1",
            "description": "Serveur de développement"
        }
    ],
    "paths": {
        "/admins/comptes": {
            "get": {
                "tags": [
                    "Admins"
                ],
                "summary": "Lister tous les comptes avec pagination et filtres (Admin)",
                "description": "Retourne la liste paginée de tous les comptes avec support pour la pagination, le tri et les filtres.",
                "operationId": "60314e3f98b2d9e5c1fcb64e00ef304b",
                "parameters": [
                    {
                        "name": "page",
                        "in": "query",
                        "description": "Numéro de la page",
                        "required": false,
                        "schema": {
                            "type": "integer",
                            "default": 1,
                            "minimum": 1
                        }
                    },
                    {
                        "name": "limit",
                        "in": "query",
                        "description": "Nombre d'éléments par page (max 100)",
                        "required": false,
                        "schema": {
                            "type": "integer",
                            "default": 10,
                            "maximum": 100,
                            "minimum": 1
                        }
                    },
                    {
                        "name": "sort",
                        "in": "query",
                        "description": "Champ de tri",
                        "required": false,
                        "schema": {
                            "type": "string",
                            "default": "created_at",
                            "enum": [
                                "created_at",
                                "solde",
                                "numeroCompte"
                            ]
                        }
                    },
                    {
                        "name": "order",
                        "in": "query",
                        "description": "Ordre de tri",
                        "required": false,
                        "schema": {
                            "type": "string",
                            "default": "desc",
                            "enum": [
                                "asc",
                                "desc"
                            ]
                        }
                    },
                    {
                        "name": "type",
                        "in": "query",
                        "description": "Filtrer par type de compte",
                        "required": false,
                        "schema": {
                            "type": "string",
                            "enum": [
                                "epargne",
                                "cheque"
                            ]
                        }
                    },
                    {
                        "name": "statut",
                        "in": "query",
                        "description": "Filtrer par statut",
                        "required": false,
                        "schema": {
                            "type": "string",
                            "enum": [
                                "actif",
                                "bloque",
                                "ferme"
                            ]
                        }
                    },
                    {
                        "name": "search",
                        "in": "query",
                        "description": "Rechercher dans numeroCompte, nom ou prenom du client",
                        "required": false,
                        "schema": {
                            "type": "string"
                        }
                    }
                ],
                "responses": {
                    "200": {
                        "description": "Liste paginée des comptes",
                        "content": {
                            "application/json": {
                                "schema": {
                                    "$ref": "#/components/schemas/CompteResponse"
                                }
                            }
                        }
                    },
                    "401": {
                        "description": "Non authentifié",
                        "content": {
                            "application/json": {
                                "schema": {
                                    "$ref": "#/components/schemas/UnauthorizedErrorResponse"
                                }
                            }
                        }
                    },
                    "500": {
                        "description": "Erreur serveur",
                        "content": {
                            "application/json": {
                                "schema": {
                                    "$ref": "#/components/schemas/ErrorResponse"
                                }
                            }
                        }
                    }
                }
            }
        },
        "/admins": {
            "post": {
                "tags": [
                    "Admins"
                ],
                "summary": "Créer un nouvel admin",
                "description": "Crée un nouvel admin avec les informations fournies.",
                "operationId": "83528520c2f718a850babe9cded3828a",
                "requestBody": {
                    "required": true,
                    "content": {
                        "application/json": {
                            "schema": {
                                "$ref": "#/components/schemas/AdminCreateRequest"
                            }
                        }
                    }
                },
                "responses": {
                    "201": {
                        "description": "Admin créé avec succès",
                        "content": {
                            "application/json": {
                                "schema": {
                                    "$ref": "#/components/schemas/AdminResponse"
                                }
                            }
                        }
                    },
                    "422": {
                        "description": "Erreurs de validation",
                        "content": {
                            "application/json": {
                                "schema": {
                                    "$ref": "#/components/schemas/ValidationErrorResponse"
                                }
                            }
                        }
                    },
                    "500": {
                        "description": "Erreur serveur",
                        "content": {
                            "application/json": {
                                "schema": {
                                    "$ref": "#/components/schemas/ErrorResponse"
                                }
                            }
                        }
                    }
                }
            }
        },
        "/comptes": {
            "get": {
                "tags": [
                    "Comptes"
                ],
                "summary": "Lister les comptes avec pagination et filtres",
                "description": "Retourne la liste des comptes avec support pour la pagination, le tri et les filtres.",
                "operationId": "3fe2756dd8a751c7a0206150450cfd1f",
                "parameters": [
                    {
                        "name": "client_id",
                        "in": "query",
                        "description": "ID du client pour filtrer les comptes",
                        "required": true,
                        "schema": {
                            "type": "string",
                            "format": "uuid",
                            "example": "72f09e5b-e8f0-42e7-87c9-b2a8cb281adb"
                        }
                    },
                    {
                        "name": "page",
                        "in": "query",
                        "description": "Numéro de la page",
                        "required": false,
                        "schema": {
                            "type": "integer",
                            "default": 1,
                            "minimum": 1
                        }
                    },
                    {
                        "name": "limit",
                        "in": "query",
                        "description": "Nombre d'éléments par page (max 100)",
                        "required": false,
                        "schema": {
                            "type": "integer",
                            "default": 10,
                            "maximum": 100,
                            "minimum": 1
                        }
                    },
                    {
                        "name": "sort",
                        "in": "query",
                        "description": "Champ de tri",
                        "required": false,
                        "schema": {
                            "type": "string",
                            "default": "created_at",
                            "enum": [
                                "created_at",
                                "solde",
                                "numeroCompte"
                            ]
                        }
                    },
                    {
                        "name": "order",
                        "in": "query",
                        "description": "Ordre de tri",
                        "required": false,
                        "schema": {
                            "type": "string",
                            "default": "desc",
                            "enum": [
                                "asc",
                                "desc"
                            ]
                        }
                    },
                    {
                        "name": "type",
                        "in": "query",
                        "description": "Filtrer par type de compte",
                        "required": false,
                        "schema": {
                            "type": "string",
                            "enum": [
                                "epargne",
                                "cheque"
                            ]
                        }
                    },
                    {
                        "name": "statut",
                        "in": "query",
                        "description": "Filtrer par statut",
                        "required": false,
                        "schema": {
                            "type": "string",
                            "enum": [
                                "actif",
                                "bloque",
                                "ferme"
                            ]
                        }
                    },
                    {
                        "name": "search",
                        "in": "query",
                        "description": "Rechercher dans numeroCompte, nom ou prenom du client",
                        "required": false,
                        "schema": {
                            "type": "string"
                        }
                    }
                ],
                "responses": {
                    "200": {
                        "description": "Liste paginée des comptes",
                        "content": {
                            "application/json": {
                                "schema": {
                                    "$ref": "#/components/schemas/CompteResponse"
                                }
                            }
                        }
                    },
                    "400": {
                        "description": "Paramètres invalides",
                        "content": {
                            "application/json": {
                                "schema": {
                                    "$ref": "#/components/schemas/ValidationErrorResponse"
                                }
                            }
                        }
                    },
                    "401": {
                        "description": "Non authentifié",
                        "content": {
                            "application/json": {
                                "schema": {
                                    "$ref": "#/components/schemas/UnauthorizedErrorResponse"
                                }
                            }
                        }
                    },
                    "500": {
                        "description": "Erreur serveur",
                        "content": {
                            "application/json": {
                                "schema": {
                                    "$ref": "#/components/schemas/ErrorResponse"
                                }
                            }
                        }
                    }
                }
            },
            "post": {
                "tags": [
                    "Comptes"
                ],
                "summary": "Créer un nouveau compte",
                "description": "Crée un nouveau compte pour un client, en créant le client si nécessaire. Le solde est calculé dynamiquement à partir des transactions.",
                "operationId": "createCompte",
                "requestBody": {
                    "required": true,
                    "content": {
                        "application/json": {
                            "schema": {
                                "required": [
                                    "type",
                                    "soldeInitial",
                                    "devise",
                                    "client"
                                ],
                                "properties": {
                                    "type": {
                                        "type": "string",
                                        "enum": [
                                            "cheque",
                                            "epargne"
                                        ],
                                        "example": "cheque"
                                    },
                                    "soldeInitial": {
                                        "type": "number",
                                        "minimum": 10000,
                                        "example": 500000
                                    },
                                    "devise": {
                                        "type": "string",
                                        "example": "FCFA"
                                    },
                                    "client": {
                                        "type": "object",
                                        "properties": {
                                            "id": {
                                                "type": "string",
                                                "format": "uuid",
                                                "nullable": true,
                                                "example": null
                                            },
                                            "titulaire": {
                                                "type": "string",
                                                "example": "Cheikh Sy"
                                            },
                                            "nci": {
                                                "type": "string",
                                                "description": "Numéro de Carte d'Identité (13 chiffres)",
                                                "example": "1234567890123"
                                            },
                                            "email": {
                                                "type": "string",
                                                "format": "email",
                                                "example": "cheikh.sy@example.com"
                                            },
                                            "telephone": {
                                                "type": "string",
                                                "description": "Numéro de téléphone portable Sénégalais (+221XXXXXXXXX)",
                                                "example": "+221771234567"
                                            },
                                            "adresse": {
                                                "type": "string",
                                                "example": "Dakar, Sénégal"
                                            }
                                        }
                                    }
                                }
                            }
                        }
                    }
                },
                "responses": {
                    "201": {
                        "description": "Compte créé avec succès",
                        "content": {
                            "application/json": {
                                "schema": {
                                    "properties": {
                                        "success": {
                                            "type": "boolean",
                                            "example": true
                                        },
                                        "message": {
                                            "type": "string",
                                            "example": "Compte créé avec succès"
                                        },
                                        "data": {
                                            "properties": {
                                                "id": {
                                                    "type": "string",
                                                    "format": "uuid",
                                                    "example": "660f9511-f30c-52e5-b827-557766551111"
                                                },
                                                "numeroCompte": {
                                                    "type": "string",
                                                    "example": "C00123460"
                                                },
                                                "titulaire": {
                                                    "type": "string",
                                                    "example": "Cheikh Sy"
                                                },
                                                "type": {
                                                    "type": "string",
                                                    "enum": [
                                                        "cheque",
                                                        "epargne"
                                                    ],
                                                    "example": "cheque"
                                                },
                                                "solde": {
                                                    "type": "number",
                                                    "format": "float",
                                                    "description": "Solde calculé à partir des transactions",
                                                    "example": 500000
                                                },
                                                "devise": {
                                                    "type": "string",
                                                    "example": "FCFA"
                                                },
                                                "dateCreation": {
                                                    "type": "string",
                                                    "format": "date-time",
                                                    "example": "2025-10-19T10:30:00Z"
                                                },
                                                "statut": {
                                                    "type": "string",
                                                    "enum": [
                                                        "actif",
                                                        "bloque",
                                                        "ferme"
                                                    ],
                                                    "example": "actif"
                                                },
                                                "codeConnexion": {
                                                    "type": "string",
                                                    "description": "Code pour la première connexion (seulement pour nouveaux clients)",
                                                    "example": "ABC123",
                                                    "nullable": true
                                                },
                                                "metadata": {
                                                    "properties": {
                                                        "derniereModification": {
                                                            "type": "string",
                                                            "format": "date-time",
                                                            "example": "2025-10-19T10:30:00Z"
                                                        },
                                                        "version": {
                                                            "type": "integer",
                                                            "example": 1
                                                        }
                                                    },
                                                    "type": "object"
                                                }
                                            },
                                            "type": "object"
                                        }
                                    },
                                    "type": "object"
                                }
                            }
                        }
                    },
                    "400": {
                        "description": "Données invalides",
                        "content": {
                            "application/json": {
                                "schema": {
                                    "properties": {
                                        "success": {
                                            "type": "boolean",
                                            "example": false
                                        },
                                        "error": {
                                            "properties": {
                                                "code": {
                                                    "type": "string",
                                                    "example": "VALIDATION_ERROR"
                                                },
                                                "message": {
                                                    "type": "string",
                                                    "example": "Les données fournies sont invalides"
                                                },
                                                "details": {
                                                    "properties": {
                                                        "titulaire": {
                                                            "type": "string",
                                                            "example": "Le nom du titulaire est requis"
                                                        },
                                                        "soldeInitial": {
                                                            "type": "string",
                                                            "example": "Le solde initial doit être supérieur ou égal à 10000"
                                                        }
                                                    },
                                                    "type": "object"
                                                }
                                            },
                                            "type": "object"
                                        }
                                    },
                                    "type": "object"
                                }
                            }
                        }
                    },
                    "500": {
                        "description": "Erreur serveur",
                        "content": {
                            "application/json": {
                                "schema": {
                                    "properties": {
                                        "success": {
                                            "type": "boolean",
                                            "example": false
                                        },
                                        "message": {
                                            "type": "string",
                                            "example": "Erreur lors de la création du compte"
                                        }
                                    },
                                    "type": "object"
                                }
                            }
                        }
                    }
                }
            }
        },
        "/clients": {
            "get": {
                "tags": [
                    "Clients"
                ],
                "summary": "Lister tous les clients",
                "description": "Retourne la liste de tous les clients.",
                "operationId": "af1f3794367a5e843bf15e3a9033d911",
                "responses": {
                    "200": {
                        "description": "Liste des clients",
                        "content": {
                            "application/json": {
                                "schema": {
                                    "type": "array",
                                    "items": {
                                        "$ref": "#/components/schemas/Client"
                                    }
                                }
                            }
                        }
                    },
                    "401": {
                        "description": "Non authentifié",
                        "content": {
                            "application/json": {
                                "schema": {
                                    "$ref": "#/components/schemas/UnauthorizedErrorResponse"
                                }
                            }
                        }
                    },
                    "500": {
                        "description": "Erreur serveur",
                        "content": {
                            "application/json": {
                                "schema": {
                                    "$ref": "#/components/schemas/ErrorResponse"
                                }
                            }
                        }
                    }
                }
            },
            "post": {
                "tags": [
                    "Clients"
                ],
                "summary": "Créer un nouveau client",
                "description": "Crée un nouveau client avec les informations fournies.",
                "operationId": "15981a5da120d8b4ea1b91b05a35622b",
                "requestBody": {
                    "required": true,
                    "content": {
                        "application/json": {
                            "schema": {
                                "$ref": "#/components/schemas/ClientCreateRequest"
                            }
                        }
                    }
                },
                "responses": {
                    "201": {
                        "description": "Client créé avec succès",
                        "content": {
                            "application/json": {
                                "schema": {
                                    "$ref": "#/components/schemas/ClientResponse"
                                }
                            }
                        }
                    },
                    "422": {
                        "description": "Erreurs de validation",
                        "content": {
                            "application/json": {
                                "schema": {
                                    "$ref": "#/components/schemas/ValidationErrorResponse"
                                }
                            }
                        }
                    },
                    "500": {
                        "description": "Erreur serveur",
                        "content": {
                            "application/json": {
                                "schema": {
                                    "$ref": "#/components/schemas/ErrorResponse"
                                }
                            }
                        }
                    }
                }
            }
        },
        "/clients/{id}": {
            "get": {
                "tags": [
                    "Clients"
                ],
                "summary": "Afficher un client spécifique",
                "description": "Retourne les détails d'un client par son ID.",
                "operationId": "2965e9737f628d15ea88209095622c24",
                "parameters": [
                    {
                        "name": "id",
                        "in": "path",
                        "description": "ID du client",
                        "required": true,
                        "schema": {
                            "type": "string"
                        }
                    }
                ],
                "responses": {
                    "200": {
                        "description": "Détails du client",
                        "content": {
                            "application/json": {
                                "schema": {
                                    "$ref": "#/components/schemas/Client"
                                }
                            }
                        }
                    },
                    "404": {
                        "description": "Client non trouvé",
                        "content": {
                            "application/json": {
                                "schema": {
                                    "$ref": "#/components/schemas/NotFoundErrorResponse"
                                }
                            }
                        }
                    },
                    "500": {
                        "description": "Erreur serveur",
                        "content": {
                            "application/json": {
                                "schema": {
                                    "$ref": "#/components/schemas/ErrorResponse"
                                }
                            }
                        }
                    }
                }
            },
            "put": {
                "tags": [
                    "Clients"
                ],
                "summary": "Mettre à jour un client",
                "description": "Met à jour les informations d'un client existant. Tous les champs sont optionnels, mais au moins un doit être modifié.",
                "security": [
                    {
                        "bearerAuth": []
                    }
                ],
                "operationId": "updateClient",
                "parameters": [
                    {
                        "name": "id",
                        "in": "path",
                        "description": "ID du client",
                        "required": true,
                        "schema": {
                            "type": "string",
                            "format": "uuid"
                        }
                    }
                ],
                "requestBody": {
                    "required": true,
                    "content": {
                        "application/json": {
                            "schema": {
                                "properties": {
                                    "titulaire": {
                                        "type": "string",
                                        "description": "Nom du titulaire",
                                        "example": "Fatou Ndiaye"
                                    },
                                    "informationsClient": {
                                        "type": "object",
                                        "properties": {
                                            "telephone": {
                                                "type": "string",
                                                "description": "Numéro de téléphone portable Sénégalais (+221XXXXXXXXX)",
                                                "example": "+221781234567"
                                            },
                                            "email": {
                                                "type": "string",
                                                "format": "email",
                                                "example": "fatou.ndiaye@example.com"
                                            },
                                            "password": {
                                                "type": "string",
                                                "minLength": 8,
                                                "example": "monNouveauMotDePasse2025"
                                            },
                                            "nci": {
                                                "type": "string",
                                                "description": "Numéro de Carte d'Identité (13 chiffres)",
                                                "example": "9876543210987"
                                            }
                                        }
                                    }
                                },
                                "type": "object"
                            },
                            "example": {
                                "titulaire": "Fatou Ndiaye",
                                "informationsClient": {
                                    "telephone": "+221781234567",
                                    "email": "fatou.ndiaye@example.com",
                                    "password": "monNouveauMotDePasse2025",
                                    "nci": "9876543210987"
                                }
                            }
                        }
                    }
                },
                "responses": {
                    "200": {
                        "description": "Client mis à jour avec succès",
                        "content": {
                            "application/json": {
                                "schema": {
                                    "properties": {
                                        "success": {
                                            "type": "boolean",
                                            "example": true
                                        },
                                        "message": {
                                            "type": "string",
                                            "example": "Client mis à jour avec succès"
                                        },
                                        "data": {
                                            "$ref": "#/components/schemas/Client"
                                        }
                                    },
                                    "type": "object"
                                }
                            }
                        }
                    },
                    "400": {
                        "description": "Aucun champ modifié",
                        "content": {
                            "application/json": {
                                "schema": {
                                    "properties": {
                                        "success": {
                                            "type": "boolean",
                                            "example": false
                                        },
                                        "message": {
                                            "type": "string",
                                            "example": "Au moins un champ doit être modifié"
                                        }
                                    },
                                    "type": "object"
                                }
                            }
                        }
                    },
                    "401": {
                        "description": "Non authentifié",
                        "content": {
                            "application/json": {
                                "schema": {
                                    "$ref": "#/components/schemas/UnauthorizedErrorResponse"
                                }
                            }
                        }
                    },
                    "404": {
                        "description": "Client non trouvé",
                        "content": {
                            "application/json": {
                                "schema": {
                                    "$ref": "#/components/schemas/NotFoundErrorResponse"
                                }
                            }
                        }
                    },
                    "422": {
                        "description": "Erreurs de validation",
                        "content": {
                            "application/json": {
                                "schema": {
                                    "$ref": "#/components/schemas/ValidationErrorResponse"
                                }
                            }
                        }
                    },
                    "500": {
                        "description": "Erreur serveur",
                        "content": {
                            "application/json": {
                                "schema": {
                                    "$ref": "#/components/schemas/ErrorResponse"
                                }
                            }
                        }
                    }
                }
            },
            "delete": {
                "tags": [
                    "Clients"
                ],
                "summary": "Supprimer un client",
                "description": "Supprime un client par son ID.",
                "operationId": "20de5e8bdef993807384fd7040f9ae92",
                "parameters": [
                    {
                        "name": "id",
                        "in": "path",
                        "description": "ID du client",
                        "required": true,
                        "schema": {
                            "type": "string"
                        }
                    }
                ],
                "responses": {
                    "200": {
                        "description": "Client supprimé avec succès",
                        "content": {
                            "application/json": {
                                "schema": {
                                    "properties": {
                                        "message": {
                                            "type": "string",
                                            "example": "Client supprimé avec succès !"
                                        }
                                    },
                                    "type": "object"
                                }
                            }
                        }
                    },
                    "404": {
                        "description": "Client non trouvé",
                        "content": {
                            "application/json": {
                                "schema": {
                                    "$ref": "#/components/schemas/NotFoundErrorResponse"
                                }
                            }
                        }
                    },
                    "500": {
                        "description": "Erreur serveur",
                        "content": {
                            "application/json": {
                                "schema": {
                                    "$ref": "#/components/schemas/ErrorResponse"
                                }
                            }
                        }
                    }
                }
            }
        }
    },
    "components": {
        "schemas": {
            "Client": {
                "properties": {
                    "id": {
                        "type": "string",
                        "format": "uuid",
                        "example": "c7917097-4734-4dfd-a462-b6c8f8d4aea3"
                    },
                    "nom": {
                        "type": "string",
                        "example": "Kilback"
                    },
                    "prenom": {
                        "type": "string",
                        "example": "Laury"
                    },
                    "titulaire": {
                        "type": "string",
                        "example": "Kilback Laury"
                    },
                    "email": {
                        "type": "string",
                        "format": "email",
                        "example": "brigitte.kuhn@example.net"
                    },
                    "telephone": {
                        "type": "string",
                        "example": "+221771234567"
                    },
                    "nci": {
                        "type": "string",
                        "description": "Numéro de Carte d'Identité (13 chiffres)",
                        "example": "1234567890123"
                    },
                    "adresse": {
                        "type": "string",
                        "example": "Dakar, Sénégal"
                    },
                    "dateCreation": {
                        "type": "string",
                        "format": "date-time",
                        "example": "2025-10-22T11:37:37.000000Z"
                    },
                    "dateModification": {
                        "type": "string",
                        "format": "date-time",
                        "example": "2025-10-22T11:37:37.000000Z"
                    }
                },
                "type": "object"
            },
            "Compte": {
                "properties": {
                    "id": {
                        "type": "string",
                        "format": "uuid",
                        "example": "281f3aa6-bffe-41bd-8c31-2b02a1e49275"
                    },
                    "numeroCompte": {
                        "type": "string",
                        "example": "23886990999492"
                    },
                    "titulaire": {
                        "type": "string",
                        "example": "Kilback Laury"
                    },
                    "type": {
                        "type": "string",
                        "enum": [
                            "epargne",
                            "cheque"
                        ],
                        "example": "cheque"
                    },
                    "solde": {
                        "type": "number",
                        "format": "float",
                        "example": 1558.59
                    },
                    "devise": {
                        "type": "string",
                        "example": "FCFA"
                    },
                    "dateCreation": {
                        "type": "string",
                        "format": "date-time",
                        "example": "2025-10-22T11:37:37.000000Z"
                    },
                    "statut": {
                        "type": "string",
                        "enum": [
                            "actif",
                            "bloque",
                            "ferme"
                        ],
                        "example": "actif"
                    },
                    "motifBlocage": {
                        "type": "string",
                        "example": "Inactivité de 30+ jours",
                        "nullable": true
                    },
                    "metadata": {
                        "properties": {
                            "derniereModification": {
                                "type": "string",
                                "format": "date-time",
                                "example": "2025-10-22T11:37:37.082038Z"
                            },
                            "version": {
                                "type": "integer",
                                "example": 1
                            }
                        },
                        "type": "object"
                    }
                },
                "type": "object"
            },
            "CompteResponse": {
                "properties": {
                    "success": {
                        "type": "boolean",
                        "example": true
                    },
                    "data": {
                        "type": "array",
                        "items": {
                            "$ref": "#/components/schemas/Compte"
                        }
                    },
                    "pagination": {
                        "properties": {
                            "currentPage": {
                                "type": "integer",
                                "example": 1
                            },
                            "totalPages": {
                                "type": "integer",
                                "example": 5
                            },
                            "totalItems": {
                                "type": "integer",
                                "example": 50
                            },
                            "hasNext": {
                                "type": "boolean",
                                "example": true
                            },
                            "hasPrevious": {
                                "type": "boolean",
                                "example": false
                            }
                        },
                        "type": "object"
                    },
                    "links": {
                        "properties": {
                            "self": {
                                "type": "string",
                                "example": "/api/v1/comptes?page=1"
                            },
                            "first": {
                                "type": "string",
                                "example": "/api/v1/comptes?page=1"
                            },
                            "last": {
                                "type": "string",
                                "example": "/api/v1/comptes?page=5"
                            },
                            "next": {
                                "type": "string",
                                "example": "/api/v1/comptes?page=2",
                                "nullable": true
                            },
                            "previous": {
                                "type": "string",
                                "example": null,
                                "nullable": true
                            }
                        },
                        "type": "object"
                    }
                },
                "type": "object"
            },
            "ClientResponse": {
                "properties": {
                    "message": {
                        "type": "string",
                        "example": "Client créé avec succès !"
                    },
                    "data": {
                        "$ref": "#/components/schemas/Client"
                    }
                },
                "type": "object"
            },
            "ClientCreateRequest": {
                "required": [
                    "nom",
                    "prenom",
                    "email",
                    "telephone"
                ],
                "properties": {
                    "nom": {
                        "type": "string",
                        "example": "Kilback"
                    },
                    "prenom": {
                        "type": "string",
                        "example": "Laury"
                    },
                    "email": {
                        "type": "string",
                        "format": "email",
                        "example": "brigitte.kuhn@example.net"
                    },
                    "telephone": {
                        "type": "string",
                        "example": "+1-201-736-0670"
                    }
                },
                "type": "object"
            },
            "ClientUpdateRequest": {
                "properties": {
                    "titulaire": {
                        "type": "string",
                        "description": "Nom du titulaire",
                        "example": "Fatou Ndiaye"
                    },
                    "informationsClient": {
                        "type": "object",
                        "properties": {
                            "telephone": {
                                "type": "string",
                                "description": "Numéro de téléphone portable Sénégalais (+221XXXXXXXXX)",
                                "example": "+221781234567"
                            },
                            "email": {
                                "type": "string",
                                "format": "email",
                                "example": "fatou.ndiaye@example.com"
                            },
                            "password": {
                                "type": "string",
                                "minLength": 8,
                                "example": "monNouveauMotDePasse2025"
                            },
                            "nci": {
                                "type": "string",
                                "description": "Numéro de Carte d'Identité (13 chiffres)",
                                "example": "9876543210987"
                            }
                        }
                    }
                },
                "type": "object",
                "example": {
                    "titulaire": "Fatou Ndiaye",
                    "informationsClient": {
                        "telephone": "+221781234567",
                        "email": "fatou.ndiaye@example.com",
                        "password": "monNouveauMotDePasse2025",
                        "nci": "9876543210987"
                    }
                }
            },
            "ErrorResponse": {
                "properties": {
                    "status": {
                        "type": "string",
                        "example": "error"
                    },
                    "message": {
                        "type": "string",
                        "example": "Une erreur est survenue"
                    },
                    "errors": {
                        "type": "object",
                        "example": null,
                        "nullable": true
                    },
                    "code": {
                        "type": "integer",
                        "example": 500
                    }
                },
                "type": "object"
            },
            "ValidationErrorResponse": {
                "properties": {
                    "status": {
                        "type": "string",
                        "example": "error"
                    },
                    "message": {
                        "type": "string",
                        "example": "Les données fournies sont invalides"
                    },
                    "errors": {
                        "properties": {
                            "nom": {
                                "type": "array",
                                "items": {
                                    "type": "string"
                                },
                                "example": [
                                    "Le champ nom est obligatoire."
                                ]
                            },
                            "email": {
                                "type": "array",
                                "items": {
                                    "type": "string"
                                },
                                "example": [
                                    "Le champ email doit être une adresse email valide."
                                ]
                            }
                        },
                        "type": "object"
                    },
                    "code": {
                        "type": "integer",
                        "example": 422
                    }
                },
                "type": "object"
            },
            "NotFoundErrorResponse": {
                "properties": {
                    "status": {
                        "type": "string",
                        "example": "error"
                    },
                    "message": {
                        "type": "string",
                        "example": "Client non trouvé"
                    },
                    "errors": {
                        "type": "object",
                        "example": null,
                        "nullable": true
                    },
                    "code": {
                        "type": "integer",
                        "example": 404
                    }
                },
                "type": "object"
            },
            "UnauthorizedErrorResponse": {
                "properties": {
                    "status": {
                        "type": "string",
                        "example": "error"
                    },
                    "message": {
                        "type": "string",
                        "example": "Non authentifié"
                    },
                    "errors": {
                        "type": "object",
                        "example": null,
                        "nullable": true
                    },
                    "code": {
                        "type": "integer",
                        "example": 401
                    }
                },
                "type": "object"
            },
            "Admin": {
                "properties": {
                    "id": {
                        "type": "string",
                        "format": "uuid",
                        "example": "c7917097-4734-4dfd-a462-b6c8f8d4aea3"
                    },
                    "nom": {
                        "type": "string",
                        "example": "Kilback"
                    },
                    "prenom": {
                        "type": "string",
                        "example": "Laury"
                    },
                    "email": {
                        "type": "string",
                        "format": "email",
                        "example": "brigitte.kuhn@example.net"
                    },
                    "telephone": {
                        "type": "string",
                        "example": "+1-201-736-0670"
                    },
                    "created_at": {
                        "type": "string",
                        "format": "date-time",
                        "example": "2025-10-22T11:37:37.000000Z"
                    },
                    "updated_at": {
                        "type": "string",
                        "format": "date-time",
                        "example": "2025-10-22T11:37:37.000000Z"
                    }
                },
                "type": "object"
            },
            "AdminResponse": {
                "properties": {
                    "message": {
                        "type": "string",
                        "example": "Admin créé avec succès !"
                    },
                    "data": {
                        "$ref": "#/components/schemas/Admin"
                    }
                },
                "type": "object"
            },
            "AdminCreateRequest": {
                "required": [
                    "nom",
                    "prenom",
                    "email",
                    "telephone"
                ],
                "properties": {
                    "nom": {
                        "type": "string",
                        "example": "Kilback"
                    },
                    "prenom": {
                        "type": "string",
                        "example": "Laury"
                    },
                    "email": {
                        "type": "string",
                        "format": "email",
                        "example": "brigitte.kuhn@example.net"
                    },
                    "telephone": {
                        "type": "string",
                        "example": "+1-201-736-0670"
                    }
                },
                "type": "object"
            }
        }
    },
    "tags": [
        {
            "name": "Admins",
            "description": "Admins"
        },
        {
            "name": "Comptes",
            "description": "Comptes"
        },
        {
            "name": "Clients",
            "description": "Clients"
        }
    ]
}